Metadata-Version: 2.1
Name: quaesit
Version: 0.0.3
Summary: Quick and easy simulation tools
Home-page: https://github.com/jgregoriods/quaesit.git
Author: Jonas Gregorio
Author-email: jonas.gregorio@gmail.com
License: MIT
Keywords: Agent-Based Model,Simulation
Platform: UNKNOWN
Classifier: Development Status :: 3 - Alpha
Classifier: Programming Language :: Python :: 3
Classifier: Programming Language :: Python :: 3.8
Classifier: License :: OSI Approved :: MIT License
Classifier: Operating System :: OS Independent
Requires-Python: >=3.8
